calcon/__init__.py
calcon/app.py
calcon/expressions.py
calcon/grammar.lark
calcon/main.py
calcon/parsing.py
calcon/prelude.calcon
calcon/statements.py
calcon-0.3.0.dist-info/entry_points.txt
calcon-0.3.0.dist-info/LICENSE
calcon-0.3.0.dist-info/METADATA
calcon-0.3.0.dist-info/WHEEL
calcon-0.3.0.dist-info/RECORD
