Metadata-Version: 2.1
Name: calcon
Version: 0.3.0
Summary: Calculator with physical quantities.
Home-page: https://github.com/ederic-oytas/calcon
License: MIT
Keywords: calculator,math,unit,quantity,dimension,physical quantity
Author: Ederic Oytas
Author-email: edericoytas@gmail.com
Requires-Python: >=3.9,<4.0
Classifier: Development Status :: 3 - Alpha
Classifier: License :: OSI Approved :: MIT License
Classifier: Programming Language :: Python :: 3
Classifier: Programming Language :: Python :: 3.9
Classifier: Programming Language :: Python :: 3.10
Classifier: Programming Language :: Python :: 3.11
Classifier: Typing :: Typed
Requires-Dist: lark (>=1.1.8,<2.0.0)
Requires-Dist: typer[all] (>=0.9.0,<0.10.0)
Project-URL: Repository, https://github.com/ederic-oytas/calcon
